{
  "db_name": "PostgreSQL",
  "query": "WITH\n    numbered_users AS (\n        SELECT\n            user_id,\n            ROW_NUMBER() OVER (\n                ORDER BY\n                    weekly_higher_or_lower_score DESC\n            ) as rn\n        FROM\n            gambling_stats\n        WHERE\n            (\n                ($1 IS TRUE)\n                OR (user_id = ANY ($2))\n            )\n            AND weekly_higher_or_lower_score > 0\n    )\nSELECT\n    rn\nFROM\n    numbered_users\nWHERE\n    user_id = $3",
  "describe": {
    "columns": [
      {
        "ordinal": 0,
        "name": "rn",
        "type_info": "Int8",
        "origin": "Expression"
      }
    ],
    "parameters": {
      "Left": [
        "Bool",
        "Int8Array",
        "Int8"
      ]
    },
    "nullable": [
      null
    ]
  },
  "hash": "c31c44b494c31f4dbb0fc4529f03eb86fb53c712a795806303f11de70ede5431"
}
